ForestStandHeightPackage/CROP_ISCE.py
ForestStandHeightPackage/CROP_ROIPAC.py
ForestStandHeightPackage/arc_sinc.py
ForestStandHeightPackage/auto_mosaicking_new.py
ForestStandHeightPackage/auto_tree_height_many.py
ForestStandHeightPackage/auto_tree_height_single_ISCE.py
ForestStandHeightPackage/auto_tree_height_single_ROIPAC.py
ForestStandHeightPackage/cal_KB.py
ForestStandHeightPackage/cal_KB_pairwise_new.py
ForestStandHeightPackage/cal_KB_self_new.py
ForestStandHeightPackage/cal_error_metric.py
ForestStandHeightPackage/cal_error_metric_pairwise.py
ForestStandHeightPackage/cal_error_metric_self.py
ForestStandHeightPackage/create_mosaic.py
ForestStandHeightPackage/extract_scatterplot_density.py
ForestStandHeightPackage/flag_scene_file.py
ForestStandHeightPackage/forest_stand_height.py
ForestStandHeightPackage/intermediate.py
ForestStandHeightPackage/intermediate_pairwise.py
ForestStandHeightPackage/intermediate_self.py
ForestStandHeightPackage/ls_deltaSC.py
ForestStandHeightPackage/mean_wo_nan.py
ForestStandHeightPackage/read_geo_data.py
ForestStandHeightPackage/read_linkfile.py
ForestStandHeightPackage/read_rsc_data.py
ForestStandHeightPackage/remove_corr_bias.py
ForestStandHeightPackage/remove_nonforest.py
ForestStandHeightPackage/remove_outlier.py
ForestStandHeightPackage/write_deltaSC.py
ForestStandHeightPackage/write_diff_height_map.py
ForestStandHeightPackage/write_file_type.py
ForestStandHeightPackage/write_mapfile_new.py
ForestStandHeightPackage-0.1.dist-info/LICENSE
ForestStandHeightPackage-0.1.dist-info/METADATA
ForestStandHeightPackage-0.1.dist-info/WHEEL
ForestStandHeightPackage-0.1.dist-info/top_level.txt
ForestStandHeightPackage-0.1.dist-info/RECORD
