Metadata-Version: 2.1
Name: ForestStandHeightPackage
Version: 0.1
Summary: code to estimate forest stand height using an interferometric SAR method
Home-page: https://github.com/leiyangleon/FSH
Author: Lei Yang
Author-email: leiyangfrancis@gmail.com
License: GNU GENERAL PUBLIC LICENSE
Platform: UNKNOWN
